Workbook
Name _options1: _Options!$A$1:$A$2
Name _options2: _Options!$B$1:$B$2
Name _options3: _Options!$C$1:$C$2
Name _options4: _Options!$D$1:$D$2
Name _options5: _Options!$E$1:$E$2
Name _options6: _Options!$F$1:$F$2
Name _options7: _Options!$G$1:$G$2
Name _options8: _Options!$H$1:$H$2

Sheet Calorie Breakdown
A1: Nutrition guidelines
A2: Your information | E2: Exercise | I2: Calorie Goals | M2: Natural Male Muscular Potential Calculator
A3: Age | B3: 32 | E3: Avg Daily Activities | F3: Time | G3: Calories | I3: Goals: | J3: Maintain Weight (Lose Fat/Gain Muscle) | M3: Wrist | N3: 7 | O3: =IF(N3<0.1045*(Q3*12+R3),"Small Boned (threshold="&ROUND(0.1045*(Q3*12+R3),2)&")","Normal Boned (threshold="&ROUND(0.1045*(Q3*12+R3),2)&")") -> Small Boned (threshold=7.42) | P3: Height | Q3: =B5 -> 5 | R3: =C5 -> 11
A4: Sex | B4: Male | E4: Elliptical trainer, moderate effort | F4: 15 | G4: =IFERROR((VLOOKUP(E4,METs!B$2:C$356,2,FALSE)*3.5*(B$6/2.205)/200)*F4,0) -> 98.214286 | I4: =IF(J20=1,K20,IF(J20=2,K21,K22)) -> In order to maintain weight, increase your Carb intake as you exercise more. Keep your fat and protein intake constant. If you're wanting to lose more fat, increase protein intake or decrease Carb intake slightly. | M4: Ankle | N4: 8.5 | O4: =IF(N4<0.1268*(Q3*12+R3),"Small Boned (threshold="&ROUND(0.1268*(Q3*12+R3),2)&")", "Normal Boned (threshold="&ROUND(0.1268*(Q3*12+R3),2)&")") -> Small Boned (threshold=9) | P4: Body Fat % | Q4: =B7 -> 0.2
A5: Height | B5: 5 | C5: 11 | E5: Resistance (weight) training, multiple exercises, 8-15 repetitions at varied resistance | F5: 45 | G5: =IFERROR((VLOOKUP(E5,METs!B$2:C$356,2,FALSE)*3.5*(B$6/2.205)/200)*F5,0) -> 206.25 | N5: Your measurements | O5: Max (Non-Elite/Bodybuilders) | P5: Hard Gainer/ Small Boned Max | Q5: Grecian Ideal | R5: Average Non-resistance Trained Male (15% bf)
A6: Weight | B6: 165 | E6: Bicycling: 12-13.9 mph, leisure, moderate effort | F6: 0 | G6: =IFERROR((VLOOKUP(E6,METs!B$2:C$356,2,FALSE)*3.5*(B$6/2.205)/200)*F6,0) -> 0 | M6: Total body weight: | N6: =B6 -> 165 | O6: =(O7/(100-$Q$4*100))*100 -> 221.25937 | P6: =(P7/(100-$Q$4*100))*100 -> 210.19643 | Q6: =ROUND((Q3*12+R3)^2/30.5689,0) & " to " & ROUND((Q3*12+R3)^2/26.5312,0) -> 165 to 190 | R6: =(R7/(100-$Q$4*100))*100 -> 178.50062 | S6: Compared to Max | T6: Compared to small boned Max | U6: Compared to Ideal (8-12% bf) | V6: Compared to Average
A7: Body Fat %: | B7: 0.2 | C7: leave blank if unknown | E7: Calisthenics (e.g., push ups, sit ups, pull-ups, jumping jacks), vigorous effort | F7: 0 | G7: =IFERROR((VLOOKUP(E7,METs!B$2:C$356,2,FALSE)*3.5*(B$6/2.205)/200)*F7,0) -> 0 | M7: Lean body mass: | N7: =N6*((100-B7*100)/100) -> 132 | O7: =(($Q$3*12+$R$3))*(($N$3/7.2546)+($N$4/5.9772))*(($Q$4*100/450)+1) -> 177.0075 | P7: =(($Q$3*12+$R$3))*(($N$3/7.6364)+($N$4/6.2918))*(($Q$4*100/450)+1) -> 168.15714 | Q7: =ROUND(((Q3*12+R3)^2/30.5689)*0.9,0) & " to " & ROUND(((Q3*12+R3)^2/26.5312)*0.9,0) -> 148 to 171 | R7: =(($Q$3*12+$R$3))*(($N$3/8.8892)+($N$4/7.3344))*((15/450)+1) -> 142.8005
E8: Walking: 3.5 mph, level, brisk, firm surface, walking for exercise | F8: 0 | G8: =IFERROR((VLOOKUP(E8,METs!B$2:C$356,2,FALSE)*3.5*(B$6/2.205)/200)*F8,0) -> 0 | M8: Chest: | N8: 41.5 | O8: =(6.3138*$N$3)*($Q$4*100/340+1) -> 46.7964 | P8: =(5.9981*$N$3)*($Q$4*100/340+1) -> 44.456506 | Q8: =0.9078*$Q$4*100+3.2719*$N$3+10.8771 -> 51.9364 | R8: =5.53*N3 -> 38.71 | S8: =(1-($N8/O8))*-1 -> -0.11317965 | T8: =(1-($N8/P8))*-1 -> -0.066503335 | U8: =(1-($N8/Q8))*-1 -> -0.20094577 | V8: =(1-($N8/R8))*-1 -> 0.072074399 | X8: chest – measured relaxed (not expanded), arms at sides, tape under armpits
E9: Exercise Calories Burned: | G9: =SUM(G4:G8) -> 304.46429 | M9: Shoulders: | N9: 48.25 | Q9: =1.0375*$Q$4*100+3.7393*$N$3+12.431 -> 59.3561 | U9: =(1-($N9/Q9))*-1 -> -0.18710967
E10: Override Average Calories Burned: | M10: Shoulder width: | N10: 20.5 | Q10: =0.42*$Q$4*100+1.5137*$N$3+5.0323 -> 24.0282 | U10: =(1-($N10/Q10))*-1 -> -0.1468358
A11: Basal Metabolic Rate | E11: Total Daily Energy Expenditure | I11: Total Calories | M11: Waist: | N11: 33 | Q11: =0.6412*$Q$4*100+2.3111*$N$3+7.6829 -> 36.6846 | U11: =(1-($N11/Q11))*-1 -> -0.10043997
M12: Hips: | N12: 38 | Q12: =0.8015*$Q$4*100+2.8888*$N$3+9.6037 -> 45.8553 | U12: =(1-($N12/Q12))*-1 -> -0.17130626
A13: =IF(B7="",(10*(B6/2.205))+(6.25*((B5*12+C5)*2.54))-(5*B3)+(IF(B4="Male",5,-161)),370+21.6*(1-B7)*B6/2.205) -> 1663.0612 | E13: =IF(G10="",A13*1.15+G9,A13*1.15+G10) -> 2216.9847 | I13: =IF(J20=1,E13*0.8,IF(J20=2,E13,E13*1.1)) -> 2216.9847 | M13: Biceps: | N13: 14.25 | O13: =(2.3008*$N$3)*($Q$4*100/265+1) -> 17.321117 | P13: =(2.1858*$N$3)*($Q$4*100/265+1) -> 16.455362 | Q13: =0.36*Q8 -> 18.697104 | R13: =1.87*N3 -> 13.09 | S13: =(1-($N13/O13))*-1 -> -0.17730479 | T13: =(1-($N13/P13))*-1 -> -0.13402089 | U13: =(1-($N13/Q13))*-1 -> -0.23784988 | V13: =(1-($N13/R13))*-1 -> 0.088617265 | X13: biceps – flexed, at largest point
M14: Forearms: | N14: 12 | O14: =(1.8514*$N$3)*($Q$4*100/340+1) -> 13.722141 | P14: =(1.7588*$N$3)*($Q$4*100/340+1) -> 13.035812 | Q14: =0.806*Q13 -> 15.069866 | R14: =1.73*N3 -> 12.11 | S14: =(1-($N14/O14))*-1 -> -0.12550091 | T14: =(1-($N14/P14))*-1 -> -0.079458938 | U14: =(1-($N14/Q14))*-1 -> -0.2037089 | V14: =(1-($N14/R14))*-1 -> -0.0090834021 | X14: forearms – fist clenched, hand out straight, measured at largest poin
A15: =IF(B7="","Calculated via 'Mifflin-St Jeor' eq.","Calculated via 'Katch-McArdle' eq.") -> Calculated via 'Katch-McArdle' eq. | E15: Calories needed to maintain weight | I15: Fat | J15: Carbs | K15: Protein | M15: Neck: | N15: 15.75 | O15: =(2.2574*$N$3)*($Q$4*100/340+1) -> 16.731318 | P15: =(2.1858*$N$3)*($Q$4*100/340+1) -> 16.200635 | Q15: =0.36*Q8 -> 18.697104 | R15: =2.19*N3 -> 15.33 | S15: =(1-($N15/O15))*-1 -> -0.058651546 | T15: =(1-($N15/P15))*-1 -> -0.027815903 | U15: =(1-($N15/Q15))*-1 -> -0.15762355 | V15: =(1-($N15/R15))*-1 -> 0.02739726 | X15: neck – relaxed, below Adam's apple at smallest point
I16: =(I13-(K16*4)-(J16*4))/9 -> 53.012892 | J16: =(B6/2.205*3)+(G9/4)+(I13-E13)/4 -> 300.60587 | K16: =IF(J20=1,B6/2.205*2.2,B6/2.205*'Studies - Protein-Carb-Fat'!K7) -> 134.3613 | M16: Thighs: | N16: 21 | O16: =(2.6785*$N$4)*($Q$4*100/190+1) -> 25.163803 | P16: =(2.5446*$N$4)*($Q$4*100/190+1) -> 23.905847 | Q16: =0.53*Q8 -> 27.526292 | R16: =2.51*N4 -> 21.335 | S16: =(1-($N16/O16))*-1 -> -0.16546794 | T16: =(1-($N16/P16))*-1 -> -0.12155383 | U16: =(1-($N16/Q16))*-1 -> -0.23709303 | V16: =(1-($N16/R16))*-1 -> -0.015701898 | X16: thighs – standing relaxed, midway between hip and knee
I17: =I16*9/$I$13 -> 0.21520944 | J17: =J16*4/$I$13 -> 0.54236886 | K17: =K16*4/$I$13 -> 0.2424217 | M17: Calves: | N17: 14.25 | O17: =(1.778*$N$4)*($Q$4*100/210+1) -> 16.552333 | P17: =(1.6891*$N$4)*($Q$4*100/210+1) -> 15.724717 | Q17: =0.679*Q16 -> 18.690352 | R17: =1.63*N4 -> 13.855 | S17: =(1-($N17/O17))*-1 -> -0.13909419 | T17: =(1-($N17/P17))*-1 -> -0.093783354 | U17: =(1-($N17/Q17))*-1 -> -0.23757456 | V17: =(1-($N17/R17))*-1 -> 0.028509563 | X17: calves – standing relaxed, at largest point
A20: Mifflin-St Jeor Equation: | E20: Calories burned = (MET*3.5*weight in kg/200)*time | I20: Lose Weight (Lose Fat/Maintain Muscle) | J20: =IF(J3="Lose Weight (Lose Fat/Maintain Muscle)",1,IF(J3="Maintain Weight (Lose Fat/Gain Muscle)",2,3)) -> 2 | K20: In order to lose weight, decrease your calorie intake by a deficit of 20%. Lower your carb intake. Keep your fat intake lower but constant. Increase your protein intake(to about 1g/pound) to promote fat loss. | N20: Calculated via formulas from Casey Butt equations from 'Your Muscular Potential'
A21: For men: | E21: 1 MET = resting oxygen cost level = 3.5 milliliters of oxygen per kilogram body weight per minute | I21: Maintain Weight (Lose Fat/Gain Muscle) | K21: In order to maintain weight, increase your Carb intake as you exercise more. Keep your fat and protein intake constant. If you're wanting to lose more fat, increase protein intake or decrease Carb intake slightly.
A22: BMR = 10W + 6.25H - 5A + 5 | I22: Gain Weight (Muscle) | K22: In order to gain weight, increase your Carb intake as you exercise more by a surplus of at least 10%. Keep your fat and protein intake constant.
A23: For women: | E23: TDEE = BMR*1.15 + calories burned
A24: BMR = 10W + 6.25H - 5A - 161
A26: Katch-McArdle Formula:
A27: BMR = 370 + 21.6(1 - F)W
A29: W = body weight in kg
A30: H = body height in cm
A31: A = age
A32: F = body fat in percentage

Sheet Studies - Protein-Carb-Fat
A2: Protein
A3: Title | B3: Macronutrient content of a hypoenergy diet affects nitrogen retention and muscle function in weight lifters. | C3: Evaluation of protein requirements for trained strength athletes | D3: Protein requirements and muscle mass/strength changes during intensive training in novice bodybuilders. | E3: Do athletes need more dietary protein and amino acids? | F3: Effect of Protein Intake on Strength, Body Composition and Endocrine Changes in Strength/Power Athletes | G3: Dietary protein for athletes: from requirements to metabolic advantage | H3: Dietary protein for athletes: from requirements to optimum adaptation. | I3: Protein “requirements” beyond the RDA: implications for optimizing health | J3: Recent developments in understanding protein needs - How much and what kind should we eat?
A4: Link | B4: https://www.ncbi.nlm.nih.gov/pubmed/3182156 | C4: https://www.researchgate.net/publication/21681796_Evaluation_of_protein_requirements_for_trained_strength_athletes | D4: https://www.ncbi.nlm.nih.gov/pubmed/1400008 | E4: https://www.ncbi.nlm.nih.gov/pubmed/7550257 | F4: https://www.ncbi.nlm.nih.gov/pmc/articles/PMC2129168/ | G4: http://www.insideoutsidespa.com/archive/phillips-dietary-protein-athletes.pdf | H4: https://www.ncbi.nlm.nih.gov/pubmed/22150425 | I4: https://www.nrcresearchpress.com/doi/10.1139/apnm-2015-0550 | J4: https://www.ncbi.nlm.nih.gov/pubmed/27109436
A5: Year | B5: 1988 | C5: 1992 | D5: 1992 | E5: 1995 | F5: 2006 | G5: 2006 | H5: 2011 | I5: 2016 | J5: 2016
A6: Study | B6: Walberg 1988 | C6: Tarnopolsky 1992 | D6: Lemon 1992 | E6: Lemon 1995 | F6: Hoffman 2006 | G6: Phillips 2006 | H6: Phillips 2011 | I6: Phillips 2016 | J6: Pencharz 2016 | K6: Averages (g/kg) | L6: Recommended Protein:
A7: Max (g/kg) | B7: 1.6 | C7: 1.76 | D7: 1.7 | E7: 1.8 | F7: 1.8 | G7: 1.7 | H7: 2 | I7: 1.6 | J7: 2.2 | K7: =AVERAGE(B7:J7) -> 1.7955556
A8: Average (g/kg) | B8: =AVERAGE(B7,B9) -> 1.6 | C8: =AVERAGE(C7,C9) -> 1.76 | D8: =AVERAGE(D7,D9) -> 1.65 | E8: =AVERAGE(E7,E9) -> 1.6 | F8: =AVERAGE(F7,F9) -> 1.7 | G8: =AVERAGE(G7,G9) -> 1.45 | H8: =AVERAGE(H7,H9) -> 1.65 | I8: =AVERAGE(I7,I9) -> 1.4 | J8: =AVERAGE(J7,J9) -> 1.85 | K8: =AVERAGE(B8:J8) -> 1.6288889 | L8: =ROUND('Calorie Breakdown'!B6/2.205*K9,0) & " - " & ROUND('Calorie Breakdown'!B6/2.205*K7,0) & "g" -> 109 - 134g | M8: Recommend using 1.8xW(kg) based on studies shown
A9: Min (g/kg) | B9: 1.6 | C9: 1.76 | D9: 1.6 | E9: 1.4 | F9: 1.6 | G9: 1.2 | H9: 1.3 | I9: 1.2 | J9: 1.5 | K9: =AVERAGE(B9:J9) -> 1.4622222
L12: Additional studies that may not include specific ranges, but look at high vs low protein intake, and health risks/benefits:
K13: 1 | L13: https://www.ncbi.nlm.nih.gov/pubmed/19927027 | M13: Increased protein intake reduces lean body mass loss during weight loss in athletes. - PubMed - NCBI | N13: 1.6g/kg vs 2.3g/kg
K14: 2 | L14: https://www.ncbi.nlm.nih.gov/pubmed/22958314 | M14: Dietary protein to maximize resistance training: a review and examination of protein spread and change theories. - PubMed - NCBI
K15: 3 | L15: https://www.ncbi.nlm.nih.gov/pubmed/17213878 | M15: Dietary protein for athletes: from requirements to metabolic advantage. - PubMed - NCBI
K16: 4 | L16: https://www.ncbi.nlm.nih.gov/pubmed/3356636 | M16: Influence of protein intake and training status on nitrogen balance and lean body mass. - PubMed - NCBI
K17: 5 | L17: https://www.ncbi.nlm.nih.gov/pubmed/26817506 | M17: Higher compared with lower dietary protein during an energy deficit combined with intense exercise promotes greater lean mass gain and fat mass los... - PubMed - NCBI
K18: 6 | L18: https://www.ncbi.nlm.nih.gov/pubmed/26778925 | M18: The effects of a high protein diet on indices of health and body composition--a crossover trial in resistance-trained men. - PubMed - NCBI
K19: 7 | L19: https://www.ncbi.nlm.nih.gov/pubmed/17277594 | M19: Effects of whey isolate, creatine, and resistance training on muscle hypertrophy. - PubMed - NCBI
K20: 8 | L20: https://www.ncbi.nlm.nih.gov/pubmed/16948480 | M20: Effect of whey and soy protein supplementation combined with resistance training in young adults. - PubMed - NCBI
K21: 9 | L21: https://www.ncbi.nlm.nih.gov/pubmed/11591884 | M21: The effect of whey protein supplementation with and without creatine monohydrate combined with resistance training on lean tissue mass and muscle s... - PubMed - NCBI
K22: 10 | L22: https://www.ncbi.nlm.nih.gov/pubmed/20798660 | M22: Effect of increased dietary protein on tolerance to intensified training. - PubMed - NCBI
K23: 11 | L23: https://www.ncbi.nlm.nih.gov/pubmed/24092765 | M23: A systematic review of dietary protein during caloric restriction in resistance trained lean athletes: a case for higher intakes. - PubMed - NCBI | N23: 1-1.4g/lb ffm
K24: 12 | L24: https://www.ncbi.nlm.nih.gov/pubmed/27807480 | M24: A High Protein Diet Has No Harmful Effects: A One-Year Crossover Study in Resistance-Trained Males. - PubMed - NCBI
K25: 13 | L25: https://www.ncbi.nlm.nih.gov/pubmed/26500462 | M25: A high protein diet (3.4 g/kg/d) combined with a heavy resistance training program improves body composition in healthy trained men and women--a fo... - PubMed - NCBI
K26: 14 | L26: https://www.ncbi.nlm.nih.gov/pubmed/24834017 | M26: The effects of consuming a high protein diet (4.4 g/kg/d) on body composition in resistance-trained individuals. - PubMed - NCBI
K27: 15 | L27: https://www.ncbi.nlm.nih.gov/pubmed/28415067 | M27: Effect of Whey Protein in Conjunction With a Caloric-Restricted Diet and Resistance Training. - PubMed - NCBI
K28: 16 | L28: https://www.ncbi.nlm.nih.gov/pubmed/28642676 | M28: International Society of Sports Nutrition Position Stand: protein and exercise. - PubMed - NCBI
K29: 17 | L29: https://www.ncbi.nlm.nih.gov/pubmed/28698222 | M29: A systematic review, meta-analysis and meta-regression of the effect of protein supplementation on resistance training-induced gains in muscle mass... - PubMed - NCBI | N29: .7g/lb bodyweight
K30: 18 | L30: https://www.ncbi.nlm.nih.gov/pubmed/28692631 | M30: Increased Protein Requirements in Female Athletes after Variable-Intensity Exercise. - PubMed - NCBI
K31: 19 | L31: https://www.ncbi.nlm.nih.gov/pubmed/30395050 | M31: Protein to Maximize Whole-Body Anabolism in Resistance-trained Females after Exercise. - PubMed - NCBI
K32: 20 | L32: https://www.ncbi.nlm.nih.gov/pubmed/28179492 | M32: Indicator Amino Acid-Derived Estimate of Dietary Protein Requirement for Male Bodybuilders on a Nontraining Day Is Several-Fold Greater than the Cu... - PubMed - NCBI
K33: 21 | L33: https://www.ncbi.nlm.nih.gov/pubmed/29497353 | M33: How much protein can the body use in a single meal for muscle-building? Implications for daily protein distribution. - PubMed - NCBI
K34: 22 | L34: https://www.ncbi.nlm.nih.gov/pubmed/27023595 | M34: Protein Considerations for Optimising Skeletal Muscle Mass in Healthy Young and Older Adults.
K35: 23 | L35: https://www.ncbi.nlm.nih.gov/pmc/articles/PMC3905294/ | M35: Protein – Which is Best?
K36: 24 | L36: https://www.ncbi.nlm.nih.gov/pubmed/22330017 | M36: Protein ingestion before sleep improves postexercise overnight recovery.
K37: 25 | L37: https://www.ncbi.nlm.nih.gov/pubmed/29764464 | M37: Daytime and nighttime casein supplements similarly increase muscle size and strength in response to resistance training earlier in the day: a preliminary investigation.
K38: 26 | L38: https://academic.oup.com/jn/article/130/7/1868S/4686204 | M38: Dietary Protein and Nitrogen Utilization | The Journal of Nutrition | Oxford Academic
K39: 27 | L39: https://examine.com/nutrition/how-much-protein-do-you-need/ | M39: How much protein do you need per day? | Examine.com
K40: 28 | L40: https://www.strongerbyscience.com/athlete-protein-intake/ | M40: Perfecting Protein Intake in Athletes: How Much, What, and When?
K41: 29 | L41: https://mennohenselmans.com/the-myth-of-1glb-optimal-protein-intake-for-bodybuilders/ | M41: The myth of 1 g/lb: Optimal protein intake for bodybuilders
A44: Carbohydrates
A45: Title | B45: Guidelines for daily carbohydrate intake: do athletes achieve them? | C45: American College of Sports Medicine position stand. Nutrition and athletic performance. | D45: ISSN exercise & sport nutrition review: research & recommendations | E45: Nutrition guidelines for strength sports: sprinting, weightlifting, throwing events, and bodybuilding. | F45: International society of sports nutrition position stand: nutrient timing.
A46: Link | B46: https://www.ncbi.nlm.nih.gov/pubmed/11310548 | C46: https://journals.lww.com/acsm-msse/Fulltext/2009/03000/Nutrition_and_Athletic_Performance.27.aspx | D46: https://www.ncbi.nlm.nih.gov/pmc/articles/PMC2853497/ | E46: https://www.tandfonline.com/doi/full/10.1080/02640414.2011.574722 | F46: https://www.ncbi.nlm.nih.gov/pubmed/28919842
A47: Year | B47: 2001 | C47: 2009 | D47: 2010 | E47: 2011 | F47: 2017
A48: Study | B48: Burke 2001 | C48: ACSM 2009 | D48: Kreider 2010 | E48: Slater 2011 | F48: Kerksick 2017 | G48: Averages (g/kg) | H48: Training Time | I48: Carb intake
A49: MAX (g/kg) extreme/endurance training | B49: 10 | C49: 10 | D49: 10 | E49: 7 | F49: 12 | G49: =AVERAGE(B49:F49) -> 9.8 | H49: >12 hours/ week | I49: =G49*('Calorie Breakdown'!$B$6/2.205) -> 733.33333 | L49: Recommended Carbs:
A50: Average (g/kg) moderate to heavy endurance training | B50: =AVERAGE(B49,B51) -> 7.5 | C50: =AVERAGE(C49,C51) -> 8 | D50: =AVERAGE(D49,D51) -> 6.5 | E50: =AVERAGE(E49,E51) -> 5.5 | F50: =AVERAGE(F49,F51) -> 8.5 | G50: =AVERAGE(B50:F50) -> 7.2 | H50: 10-12 hours/ week | I50: =G50*'Calorie Breakdown'!$B$6/2.205 -> 538.77551 | L50: =ROUND('Calorie Breakdown'!B6/2.205*G54,0) & " - " & ROUND('Calorie Breakdown'!B6/2.205*G49,0) & "g" -> 224 - 733g | M50: Use 3xW(kg) as the base, and add based on Exersice METs.
A51: MIN (g/kg) general/moderate duration/low-intensity training | B51: 5 | C51: 6 | D51: 3 | E51: 4 | F51: 5 | G51: =AVERAGE(B51:F51) -> 4.6 | H51: 8-10 hours/ week | I51: =G51*'Calorie Breakdown'!$B$6/2.205 -> 344.21769
F52: WIP | G52: 4.5 | H52: 4-6 hours/week | I52: =G52*'Calorie Breakdown'!$B$6/2.205 -> 336.73469 | J52: my opinion/correlation | L52: Additional Studies
F53: WIP | G53: 3.3 | H53: 1-3 hours/week | I53: =G53*'Calorie Breakdown'!$B$6/2.205 -> 246.93878 | J53: my opinion/correlation | K53: 1 | L53: https://www.ncbi.nlm.nih.gov/pubmed/15107010 | M53: Macronutrient considerations for the sport of bodybuilding
G54: 3 | H54: Sedentary (no exercise) | I54: =G54*'Calorie Breakdown'!$B$6/2.205 -> 224.4898 | J54: Use this as the base and add based on Exersice METs | K54: 2 | L54: https://www.ncbi.nlm.nih.gov/pmc/articles/PMC4033492/ | M54: Evidence-based recommendations for natural bodybuilding contest preparation: nutrition and supplementation
H55: NEED to find source again | K55: 3 | L55: https://www.ncbi.nlm.nih.gov/pubmed/14971430 | M55: Carbohydrates and fat for training and recovery. (http://www.sportsnutritionworkshop.com/files/38.spnt.pdf)
K56: 4 | L56: https://www.ncbi.nlm.nih.gov/pubmed/2289498 | M56: Glycogen and triglyceride utilization in relation to muscle metabolic characteristics in men performing heavy-resistance exercise.
K57: 5 | L57: https://www.ncbi.nlm.nih.gov/pubmed/1901662 | M57: Regulation of glycogen resynthesis following exercise. Dietary considerations.
K58: 6 | L58: https://www.ncbi.nlm.nih.gov/pubmed/2055849 | M58: Muscle glycogenolysis during differing intensities of weight-resistance exercise.
K59: 7 | L59: https://www.ncbi.nlm.nih.gov/pubmed/24066806 | M59: Is carbohydrate needed to further stimulate muscle protein synthesis/hypertrophy following resistance exercise?
K60: 8 | L60: https://www.ncbi.nlm.nih.gov/pubmed/24864135 | M60: Evidence-based recommendations for natural bodybuilding contest preparation: nutrition and supplementation.
K61: 9 | L61: https://www.ncbi.nlm.nih.gov/pubmed/27182422 | M61: Increasing Lean Mass and Strength: A Comparison of High Frequency Strength Training to Lower Frequency Strength Training.
K62: 10 | L62: https://www.ncbi.nlm.nih.gov/pmc/articles/PMC5794245/ | M62: High-Quality Carbohydrates and Physical Performance
K63: 11 | L63: https://www.ncbi.nlm.nih.gov/pubmed/2055827/ | M63: Dietary carbohydrate, muscle glycogen, and power output during rowing training.
K64: 12 | L64: https://www.ncbi.nlm.nih.gov/pmc/articles/PMC5371625/ | M64: Periodized Nutrition for Athletes
K65: 13 | L65: https://www.ncbi.nlm.nih.gov/pmc/articles/PMC4672006/ | M65: Carbohydrate Dependence During Prolonged, Intense Endurance Exercise
K66: 14 | L66: https://www.ncbi.nlm.nih.gov/pubmed/20739718/ | M66: Race-day carbohydrate intakes of elite triathletes contesting olympic-distance triathlon events.
K67: 15 | L67: https://www.ncbi.nlm.nih.gov/pubmed/14660506/ | M67: Higher dietary carbohydrate content during intensified running training results in better maintenance of performance and mood state.
... K82: 30 | L82: https://www.menshealth.com/health/a25924744/keto-diet-carbs-muscle-exercise/ | M82: Here's How the Keto Diet Affects Your Ability to Build Muscle
J83: Glucose
J84: Glucose (Benefits) [1st Phorm linked studies] | L84: http://webcache.googleusercontent.com/search?q=cache:https://1stphorm.com/blog/i-have-been-using-ignition-for-the-last-6-months-and-it-has-worked-amazing-i-do-have-one-question-about-the-main-ingredient-i-was-doing-some-reading-online-and-was-wondering-what-is-the-difference-b/&ved=2ahUKEwjdqr-bgOblAhWJ2FkKHRFnCSQQFjAAegQIAxAB&usg=AOvVaw2DsDBE9uXPFYIyNRSTYecF&cshid=1573607817095 | M84: I have been using Ignition for the last 6 months and it has worked amazing! I do have one question about the main ingredient: I was doing some reading online and was wondering what is the difference between Dexanhdyrous Glucose, Dextrose and Pure Glucose?
K85: 1 | L85: https://www.physiology.org/doi/full/10.1152/jappl.2000.88.5.1529 | M85: Effect of different carbohydrate drinks on whole body carbohydrate storage after exhaustive exercise
K86: 2 | L86: https://pdfs.semanticscholar.org/5960/293f5676e49330b4b5b7a3bb98714de0ab8b.pdf | M86: Effect of glucose supplement timing on protein metabolism after resistance training
K87: 3 | L87: https://pdfs.semanticscholar.org/791d/fd5ab346f224465cca6fd16b3c4560a56b95.pdf | M87: Carbohydrate Supplementation and Resistance Training
J88: Glucose (Benefits) | L88: https://www.bodybuilding.com/content/post-workout-carbs.html | M88: Post-Workout Carbs: Best Choices To Grow And Recover!
K89: 4 | L89: https://www.ncbi.nlm.nih.gov/pubmed/8904559 | M89: Muscle glycogen recovery after exercise during glucose and fructose intake monitored by 13C-NMR.
I90: i | K90: 5 | L90: https://www.ncbi.nlm.nih.gov/pmc/articles/PMC3905295/ | M90: Regulation of Muscle Glycogen Repletion, Muscle Protein Synthesis and Repair Following Exercise
K91: 6 | L91: https://www.ncbi.nlm.nih.gov/pmc/articles/PMC5409683/ | M91: Glucose Plus Fructose Ingestion for Post-Exercise Recovery—Greater than the Sum of Its Parts?
J92: Glucose (No Benefits) | K92: 1 | L92: https://journals.lww.com/acsm-msse/fulltext/2011/07000/Carbohydrate_Does_Not_Augment_Exercise_Induced.4.aspx | M92: Carbohydrate Does Not Augment Exercise-Induced Protein Accretion versus Protein Alone
K93: 2 | L93: https://www.ncbi.nlm.nih.gov/pubmed/17609259 | M93: Coingestion of carbohydrate with protein does not further augment postexercise muscle protein synthesis.
K94: 3 | L94: https://www.ncbi.nlm.nih.gov/pmc/articles/PMC3850644/ | M94: Is carbohydrate needed to further stimulate muscle protein synthesis/hypertrophy following resistance exercise?
J95: Glutamine
J96: Glutamine (No Benefits) | K96: 1 | L96: https://www.healthline.com/nutrition/glutamine | M96: Glutamine: Benefits, Uses and Side Effects
K97: 2 | L97: https://examine.com/nutrition/does-glutamine-build-muscle/ | M97: Fact check: does glutamine build muscle?
K98: 3 | L98: https://www.ncbi.nlm.nih.gov/pubmed/11822473 | M98: Effect of glutamine supplementation combined with resistance training in young adults.
K99: 4 | L99: https://www.ncbi.nlm.nih.gov/pubmed/11834123 | M99: The effects of high-dose glutamine ingestion on weightlifting performance.
K100: 5 | L100: https://www.ncbi.nlm.nih.gov/pubmed/17111006 | M100: Addition of glutamine to essential amino acids and carbohydrate does not enhance anabolism in young human males following exercise.
K101: 6 | L101: https://academic.oup.com/jn/article/138/10/2045S/4670120 | M101: Dosing and Efficacy of Glutamine Supplementation in Human Exercise and Sport Training
J102: Glutamine (Benefits) | K102: 1 | L102: https://www.ncbi.nlm.nih.gov/pubmed/25811544 | M102: The Influence of Oral L-Glutamine Supplementation on Muscle Strength Recovery and Soreness Following Unilateral Knee Extension Eccentric Exercise.
K103: 2 | L103: https://www.nutritionexpress.com/article+index/sports+nutrition/muscle+recovery/showarticle.aspx?id=281 | M103: L-glutamine can help stimulate metabolism and speed recovery
A106: Fat
A107: Title | B107: ISSN exercise & sport nutrition review: research & recommendations
A108: Link | B108: https://www.ncbi.nlm.nih.gov/pmc/articles/PMC2853497/
A109: Year | B109: 2010
A110: Study | B110: Kreider 2010 | G110: Averages (g/kg) | L110: Recommended Fats:
A111: MAX (g/kg) | B111: 1.1 | G111: =AVERAGE(B111:F111) -> 1.1 | H111: To maintain body fat (20-30% of total calories) Boost more fat if testosterone is low
A112: Average (g/kg) | B112: =AVERAGE(B111,B113) -> 0.8 | G112: =AVERAGE(B112:F112) -> 0.8 | L112: =ROUND('Calorie Breakdown'!B6/2.205*G113,0) & " - " & ROUND('Calorie Breakdown'!B6/2.205*G111,0) & "g" -> 37 - 82g | M112: Not a lot of fat recommendation studies as you can see. My calculation for recommended fat basically fills the remainder of your calories with healthy fats after factoring in the recommended Protein and Carb intakes.
A113: MIN (g/kg) | B113: 0.5 | G113: =AVERAGE(B113:F113) -> 0.5 | H113: To lose body fat (15-20% of total calories, or 0.5 - 1 g/kg/d)
L114: Additional Studies
K115: 1 | L115: https://www.ncbi.nlm.nih.gov/pubmed/12037719 | M115: Effects of high-fat and high-carbohydrate diets on metabolism and performance in cycling.
K116: 2 | L116: https://www.ncbi.nlm.nih.gov/pubmed/12783043 | M116: Effects of dietary fat on muscle substrates, metabolism, and performance in athletes.
K117: 3 | L117: https://www.ncbi.nlm.nih.gov/pubmed/14598198 | M117: Maximal fat oxidation during exercise in trained men.
K118: 4 | L118: https://www.ncbi.nlm.nih.gov/pubmed/20932294 | M118: Effects of supplemental fish oil on resting metabolic rate, body composition, and salivary cortisol in healthy adults.
K119: 5 | L119: https://www.ncbi.nlm.nih.gov/pmc/articles/PMC4033492/ | M119: Evidence-based recommendations for natural bodybuilding contest preparation: nutrition and supplementation | N119: 15-20-30% (or 0.66g/kg FFM?)
K120: 6 | L120: https://www.ncbi.nlm.nih.gov/pubmed/10584044/ | M120: Dietary saturated fats and their food sources in relation to the risk of coronary heart disease in women.
K121: 7 | L121: https://www.ncbi.nlm.nih.gov/pubmed/21558571 | M121: Effect of two different weight-loss rates on body composition and strength and power-related performance in elite athletes. | N121: high-protein, high-carb, low-fat diet lose less muscle than those following a high-protein, low-carb, high-fat diet.
...

Sheet METs
A1: ACTIVITY | B1: SPECIFIC MOTION | C1: METs | D1: CALORIES BURNED = (MET*3.5*weight in kg/200)*time | L1: Lose Weight/Fat
A2: running | B2: Running: 6 mph (10 min/mile) | C2: 9.8
A3: running | B3: Running: 6.7 mph (9 min/mile) | C3: 10.5
A4: running | B4: Running: 7.5 mph (8 min/mile) | C4: 11.5
A5: bicycling | B5: Bicycling: 12-13.9 mph, leisure, moderate effort | C5: 8
A6: bicycling | B6: Bicycling: mountain, general | C6: 8.5
A7: conditioning exercise | B7: Calisthenics (e.g., push ups, sit ups, pull-ups, jumping jacks), vigorous effort | C7: 8
A8: conditioning exercise | B8: Elliptical trainer, moderate effort | C8: 5
A9: conditioning exercise | B9: Resistance (weight) training, multiple exercises, 8-15 repetitions at varied resistance | C9: 3.5
A10: conditioning exercise | B10: Yoga, Power | C10: 4
A11: walking | B11: Walking: 3.5 mph, level, brisk, firm surface, walking for exercise | C11: 4.3
A12: running | B12: Running: jog/walk combination (jogging component of less than 10 minutes) | C12: 6
A13: running | B13: Running: jogging, general | C13: 7
... A356: winter activities | B356: Winter Activities: snowmobiling, passenger | C356: 2
A358: Other Activities
A359: dancing | B359: aerobic dance wearing 10-15 lb weights | C359: 10
A360: dancing | B360: aerobic, general | C360: 7.3
A361: dancing | B361: aerobic, high impact | C361: 7.3
A362: dancing | B362: aerobic, low impact | C362: 5
A363: dancing | B363: aerobic, step, with 10 – 12 inch step | C363: 9.5
A364: dancing | B364: aerobic, step, with 4-inch step | C364: 5.5
A365: dancing | B365: aerobic, step, with 6 – 8 inch step | C365: 7.5
A366: dancing | B366: Anishinaabe Jingle Dancing | C366: 5.5
A367: dancing | B367: ballet, modern, or jazz, general, rehearsal or class | C367: 5
A368: dancing | B368: ballet, modern, or jazz, performance, vigorous effort | C368: 6.8
A369: dancing | B369: ballroom dancing, competitive, general | C369: 11.3
A370: dancing | B370: ballroom, fast | C370: 5.5
... A750: transportation | B750: walking for transportation, 2.8-3.2 mph, level, moderate pace, firm surface | C750: 3.5

Sheet _SSC
A1: _Ctrl_1 | D1: {"InputDetection":0,"RecalcMode":0,"Layout":0,"LayoutSamePagesHeightEnabled":false,"Theme":{"BgColor":"#FFFFFFFF","BgImage":"","InputBorderStyle":2,"AppliedTheme":""},"SmartphoneSettings":{"ViewportLock":true,"UseOldViewEngine":false,"EnableZoom":false,"EnableSwipe":false,"HideToolbar":false,"InheritBackgroundColor":false,"CheckboxFlavor":1,"ShowBubble":false},"Name":"","Flavor":-1,"Edition":0,"CopyProtect":{"IsEnabled":false,"DomainName":""},"HideSscPoweredlogo":false,"AspnetConfig":{"BrowseUrl":"http://localhost/ssc","FileExtension":0},"NodeSecureLoginEnabled":false,"SmartphoneTheme":1,"Toolbar":{"Position":1,"IsSubmit":false,"IsPrintSheet":false,"IsPrintAll":false,"IsPrintThis":false,"IsReset":false,"IsUpdate":false},"ConfigureSubmit":{"IsShowCaptcha":false,"IsUseSscWebServer":true,"ReceiverCode":"","IsFreeService":false,"IsAdvanceService":false,"IsSecureEmail":false,"IsDemonstrationService":true,"AfterSuccessfulSubmit":"","AfterFailSubmit":"","AfterCancelWizard":"","IsUseOwnWebServer":false,"OwnWebServerURL":"","OwnWebServerTarget":"","SubmitTarget":0},"IgnoreBgInputCell":false,"ButtonStyle":0,"ResponsiveDesignDisabled":false,"HideLookupRange":false,"BrowserStorageEnabled":false,"RealtimeSyncEnabled":false,"GoogleAnalyticsTrackingId":"","GoogleApiKey":"","ChartSelected":3,"ChartYAxisFixed":false} | E1: {"BrowserAndLocation":{"ConversionPath":"D:\\Documents\\SpreadsheetConverter","SelectedBrowsers":[]},"SpreadsheetServer":{"Username":"","Password":"","ServerUrl":"","TestUsername":"","TestPassword":""},"ConfigureSubmitDefault":{"Email":"","Free":false,"Advanced":false,"AdvancedSecured":false,"Demo":true},"MessageBubble":{"Close":false,"TopMsg":0},"CustomizeTheme":{"Theme":"C:\\Users\\user\\AppData\\Roaming\\SpreadsheetConverter\\V8\\SupportFiles\\themes\\bootstrap\\css\\default-ssc-theme.css"},"QrSetting":{"ShowOnConversion":true},"CongratsPage":{"LastOpenedVersion":""},"WordPressPluginSetting":{"IsPluginInstalled":false},"Preferences":{"IsAdvancedSettingModelInitialize":true,"IsCaptchaInitialize":true,"IsNodeSettingInitialize":false,"IsRequiredFieldModalInitialize":true,"IsSubmitDialogModelInitialize":true,"IsToolbarButtonModelInitialize":true,"IsWizardButtonModelInitialize":true,"ReadFromHidden":false,"AdvancedSetting":null,"NodeSetting":{"LoginText":{"LoginButtonText":"Login","PageDescription":"Restricted access only","LoginErrorMessage":"Authentication failed, please check your username and password.","PlaceholderPassword":"password","PlaceholderUsername":"username / email","UserExtraMessage":""}},"Captcha":{"Heading":"Enter the number displayed below.","Message":"This is to verify that you are a human visitor, to prevent automated form submissions.","OkButton":"OK","CancelButton":"Cancel","ErrorMessage":"Your answer is incorrect, please try again."},"RequiredField":{"ErrorMessage":"The fields with the red border are required or invalid.","OkButton":"OK","DDLDefaultRequiredText":"Please Select"},"WizardButton":{"Next":"Next","Previous":"Previous","Cancel":"Cancel","Finish":"Finish"},"ToolbarButton":{"Submit":"Submit","PrintSheet":"Print","PrintAll":"Print All","Reset":"Reset","Update":"Update","Back":"Back","PrintThis":"Print This"},"SubmitDialog":{"SubmitDialogHeading":"Submit Successful.","SubmitDialogDesc":"The form was successfully submitted.","BeforeSubmitDesc":"The form is being submitted.","OfflineHeading":"Save until online","OfflineDesc":"You are currently offline and the submit failed. Do you want to save the submit and send it later when you are online.","OfflineConfirm":"Do you want to save?","OfflineSubmitHeading":"Offline forms submit confirmation","OfflineSubmitDesc":"There are Offline form(s), which are now ready to submit in server.","OfflineSubmitConfirm":"Do you want to submit?","FailOfflineHeading":"Offline Form submit failed","FailOfflineDesc":"Unable to connect to the Internet. Please try submitting the offline forms later in internet connection.","OfflineSubmitWait":"It may take sometime to finish all submits depending on the size of offline forms and internet connection.","OfflineSubmitWaitCounter":"Left","OfflineSubmitError":"Submit error: Please try later."}},"UxPreferences":null}
A2: _Ctrl_2 | B2: {"WidgetClassification":0,"State":1,"IsRequired":true,"ListItem":"Male\r\nFemale","VlookupRange":"","Direction":1,"Rows":1,"Columns":2,"CellName":"_Ctrl_2","CellAddress":"='Calorie Breakdown'!$B$4","WidgetName":7,"HiddenRow":2,"SheetCodeName":null,"ControlId":"sex","wcb":0}

Sheet _Options
A1: Male | B1: Male | C1: Male | D1: Male | E1: Male | F1: Male | G1: Male | H1: Male
A2: Female | B2: Female | C2: Female | D2: Female | E2: Female | F2: Female | G2: Female | H2: Female
